irs_asset_fifo_calculator/__init__.py
irs_asset_fifo_calculator/calculate_taxes.py
irs_asset_fifo_calculator/py.typed
irs_asset_fifo_calculator-1.0.0.dist-info/licenses/LICENSE
irs_asset_fifo_calculator-1.0.0.dist-info/METADATA
irs_asset_fifo_calculator-1.0.0.dist-info/WHEEL
irs_asset_fifo_calculator-1.0.0.dist-info/entry_points.txt
irs_asset_fifo_calculator-1.0.0.dist-info/top_level.txt
irs_asset_fifo_calculator-1.0.0.dist-info/RECORD
