Metadata-Version: 2.4
Name: irs-asset-fifo-calculator
Version: 1.0.0
Summary: FIFO-based IRS Form 8949 capital gains calculator for assets.
Author-email: Elliott Bache <elliottbache@gmail.com>
License:                     GNU GENERAL PUBLIC LICENSE
Project-URL: Homepage, https://github.com/elliottbache/irs_asset_fifo_calculator
Project-URL: Source, https://github.com/elliottbache/irs_asset_fifo_calculator
Project-URL: Issues, https://github.com/elliottbache/irs_asset_fifo_calculator/issues
Project-URL: Documentation, https://elliottbache.github.io/irs_asset_fifo_calculator/
Keywords: taxes,IRS,capital-gains,FIFO
Requires-Python: >=3.11
License-File: LICENSE
Requires-Dist: pandas>=2.0
Requires-Dist: pyarrow
Provides-Extra: dev
Requires-Dist: pytest>=9.0; extra == "dev"
Requires-Dist: sphinx>=8.0; extra == "dev"
Requires-Dist: sphinx-autodoc-typehints; extra == "dev"
Requires-Dist: sphinx_rtd_theme; extra == "dev"
Requires-Dist: myst-parser>=3.0; extra == "dev"
Requires-Dist: pre-commit; extra == "dev"
Requires-Dist: ruff; extra == "dev"
Requires-Dist: black==25.12.0; extra == "dev"
Requires-Dist: isort; extra == "dev"
Requires-Dist: mypy; extra == "dev"
Requires-Dist: codespell; extra == "dev"
Requires-Dist: pytest-cov; extra == "dev"
Requires-Dist: pandas-stubs; extra == "dev"
Dynamic: license-file
